lethbridge/__init__.py
lethbridge/__main__.py
lethbridge/config.py
lethbridge/database.py
lethbridge/cli/__init__.py
lethbridge/cli/configure.py
lethbridge/cli/database.py
lethbridge/cli/import.py
lethbridge/migrations/env.py
lethbridge/migrations/versions/549d345a9779.py
lethbridge/migrations/versions/a41aac16b9b4.py
lethbridge/migrations/versions/f6b71224e220.py
lethbridge/schemas/__init__.py
lethbridge/schemas/spansh.py
lethbridge-0.2.3.dist-info/LICENSE
lethbridge-0.2.3.dist-info/METADATA
lethbridge-0.2.3.dist-info/WHEEL
lethbridge-0.2.3.dist-info/entry_points.txt
lethbridge-0.2.3.dist-info/top_level.txt
lethbridge-0.2.3.dist-info/RECORD
