Metadata-Version: 2.1
Name: lethbridge
Version: 0.2.3
Summary: SQLAlchemy ORM and Marshmallow schemas for Elite: Dangerous game data
License: GNU AFFERO GENERAL PUBLIC LICENSE
Classifier: Development Status :: 2 - Pre-Alpha
Classifier: Environment :: Console
Classifier: Environment :: No Input/Output (Daemon)
Classifier: Intended Audience :: Developers
Classifier: License :: OSI Approved :: GNU Affero General Public License v3 or later (AGPLv3+)
Classifier: Operating System :: OS Independent
Classifier: Programming Language :: Python
Classifier: Topic :: Database :: Front-Ends
Classifier: Topic :: Games/Entertainment :: Simulation
Classifier: Topic :: Utilities
Requires-Python: >=3.10
License-File: LICENSE
Requires-Dist: alembic[tz]
Requires-Dist: colorama
Requires-Dist: marshmallow-sqlalchemy
Requires-Dist: shellingham
Requires-Dist: simplejson
Requires-Dist: sqlalchemy >=2
Requires-Dist: typer
Provides-Extra: dev
Requires-Dist: autopep8 ; extra == 'dev'
Requires-Dist: black ; extra == 'dev'
Requires-Dist: build ; extra == 'dev'
Requires-Dist: flake8 ; extra == 'dev'
Requires-Dist: isort ; extra == 'dev'
Requires-Dist: id ; extra == 'dev'
Requires-Dist: jedi ; extra == 'dev'
Requires-Dist: pre-commit ; extra == 'dev'
Requires-Dist: python-semantic-release ; extra == 'dev'
Requires-Dist: twine ; extra == 'dev'
Requires-Dist: yapf ; extra == 'dev'
Provides-Extra: psycopg2
Requires-Dist: psycopg2 ; extra == 'psycopg2'
Provides-Extra: psycopg2cffi
Requires-Dist: psycopg2cffi ; extra == 'psycopg2cffi'
Provides-Extra: test
Requires-Dist: pytest ; extra == 'test'
Requires-Dist: pytest-cov ; extra == 'test'
Requires-Dist: pytest-emoji ; extra == 'test'
Requires-Dist: pytest-md ; extra == 'test'
Requires-Dist: pytest-order ; extra == 'test'
Requires-Dist: pytest-postgresql ; extra == 'test'
Requires-Dist: pytest-reportlog ; extra == 'test'
Requires-Dist: python-dateutil >=2.8.2 ; extra == 'test'
